kataven/__init__.py
kataven-0.0.2.dist-info/licenses/LICENSE
kataven-0.0.2.dist-info/METADATA
kataven-0.0.2.dist-info/WHEEL
kataven-0.0.2.dist-info/top_level.txt
kataven-0.0.2.dist-info/RECORD
