Metadata-Version: 2.4
Name: kataven
Version: 0.0.2
Summary: Kataven - Coming Soon
Author-email: Kataven <support@kataven.ai>
Project-URL: Homepage, https://github.com/kataven/kataven
Keywords: kataven
Classifier: Development Status :: 1 - Planning
Classifier: Intended Audience :: Developers
Classifier: License :: OSI Approved :: MIT License
Classifier: Programming Language :: Python :: 3
Classifier: Programming Language :: Python :: 3.8
Classifier: Programming Language :: Python :: 3.9
Classifier: Programming Language :: Python :: 3.10
Classifier: Programming Language :: Python :: 3.11
Classifier: Programming Language :: Python :: 3.12
Requires-Python: >=3.8
License-File: LICENSE
Dynamic: license-file
